LICENSE
README.md
setup.cfg
setup.py
twinpy.egg-info/PKG-INFO
twinpy.egg-info/SOURCES.txt
twinpy.egg-info/dependency_links.txt
twinpy.egg-info/requires.txt
twinpy.egg-info/top_level.txt
twinpy/twincat/__init__.py
twinpy/twincat/connection.py
twinpy/twincat/pyads_extra.py
twinpy/twincat/simulink.py
twinpy/twincat/symbols.py
twinpy/ui/__init__.py
twinpy/ui/base_gui.py
twinpy/ui/base_widgets.py
twinpy/ui/custom_widgets.py
twinpy/ui/tabs.py
twinpy/ui/tc_base.py
twinpy/ui/tc_widgets.py