Metadata-Version: 2.1
Name: twinpy
Version: 1.2.0
Summary: Package to interface with TwinCAT (incl. Simulink models)
Home-page: https://bitbucket.org/ctw-bw/twinpy
Author: Robert Roos
Author-email: robert.soor@gmail.com
License: MIT
Platform: UNKNOWN
Classifier: Programming Language :: Python :: 3
Classifier: Programming Language :: Python :: 3.6
Classifier: License :: OSI Approved :: MIT License
Classifier: Operating System :: OS Independent
Classifier: Development Status :: 4 - Beta
Classifier: Intended Audience :: Developers
Requires-Python: >=3.6
License-File: LICENSE
